parsl/__init__.py
parsl/addresses.py
parsl/config.py
parsl/curvezmq.py
parsl/errors.py
parsl/log_utils.py
parsl/multiprocessing.py
parsl/process_loggers.py
parsl/py.typed
parsl/utils.py
parsl/version.py
parsl/app/__init__.py
parsl/app/app.py
parsl/app/bash.py
parsl/app/errors.py
parsl/app/futures.py
parsl/app/python.py
parsl/benchmark/__init__.py
parsl/benchmark/perf.py
parsl/concurrent/__init__.py
parsl/configs/ASPIRE1.py
parsl/configs/Azure.py
parsl/configs/__init__.py
parsl/configs/anvil.py
parsl/configs/bridges.py
parsl/configs/cc_in2p3.py
parsl/configs/delta.py
parsl/configs/ec2.py
parsl/configs/expanse.py
parsl/configs/frontera.py
parsl/configs/gc_multisite.py
parsl/configs/gc_tutorial.py
parsl/configs/htex_local.py
parsl/configs/illinoiscluster.py
parsl/configs/improv.py
parsl/configs/kubernetes.py
parsl/configs/local_threads.py
parsl/configs/midway.py
parsl/configs/osg.py
parsl/configs/polaris.py
parsl/configs/stampede2.py
parsl/configs/summit.py
parsl/configs/toss3_llnl.py
parsl/configs/vineex_local.py
parsl/configs/wqex_local.py
parsl/data_provider/__init__.py
parsl/data_provider/data_manager.py
parsl/data_provider/file_noop.py
parsl/data_provider/files.py
parsl/data_provider/ftp.py
parsl/data_provider/globus.py
parsl/data_provider/http.py
parsl/data_provider/rsync.py
parsl/data_provider/staging.py
parsl/data_provider/zip.py
parsl/dataflow/__init__.py
parsl/dataflow/dependency_resolvers.py
parsl/dataflow/dflow.py
parsl/dataflow/errors.py
parsl/dataflow/futures.py
parsl/dataflow/memoization.py
parsl/dataflow/rundirs.py
parsl/dataflow/states.py
parsl/dataflow/taskrecord.py
parsl/executors/__init__.py
parsl/executors/base.py
parsl/executors/errors.py
parsl/executors/execute_task.py
parsl/executors/globus_compute.py
parsl/executors/status_handling.py
parsl/executors/threads.py
parsl/executors/flux/__init__.py
parsl/executors/flux/execute_parsl_task.py
parsl/executors/flux/executor.py
parsl/executors/flux/flux_instance_manager.py
parsl-2026.1.5.dist-info/licenses/LICENSE
parsl-2026.1.5.dist-info/METADATA
parsl-2026.1.5.dist-info/WHEEL
parsl-2026.1.5.dist-info/entry_points.txt
parsl-2026.1.5.dist-info/top_level.txt
parsl-2026.1.5.dist-info/RECORD
